MenuMate/Menu.py
MenuMate/MenuItem.py
MenuMate/MenuManager.py
MenuMate/__init__.py
MenuMate-1.0.3.dist-info/METADATA
MenuMate-1.0.3.dist-info/WHEEL
MenuMate-1.0.3.dist-info/top_level.txt
MenuMate-1.0.3.dist-info/RECORD
