Metadata-Version: 2.1
Name: MenuMate
Version: 1.0.3
Summary: Modular Terminal Menu Library
Home-page: https://github.com/bethChris/MenuMate
Author: Bethany Christensen
Author-email: bethiehc@gmail.com
License: MIT
Classifier: Intended Audience :: Developers
Classifier: License :: OSI Approved :: MIT License
Classifier: Programming Language :: Python
Classifier: Programming Language :: Python :: 3
Classifier: Programming Language :: Python :: 3.6
Classifier: Programming Language :: Python :: 3.7
Classifier: Programming Language :: Python :: 3.8
Classifier: Programming Language :: Python :: 3.9
Classifier: Operating System :: OS Independent
